flowright/__init__.py
flowright/client.py
flowright/commands.py
flowright/components.py
flowright/config.py
flowright/customization.py
flowright/messages.py
flowright/res/client.html
flowright/server.py
flowright-0.1.4.dist-info/METADATA
flowright-0.1.4.dist-info/WHEEL
flowright-0.1.4.dist-info/entry_points.txt
flowright-0.1.4.dist-info/RECORD
