Metadata-Version: 2.1
Name: flowright
Version: 0.1.4
Summary: 
Author: ReeceJones
Author-email: reece_jones@icloud.com
Requires-Python: >=3.11,<4.0
Classifier: Programming Language :: Python :: 3
Classifier: Programming Language :: Python :: 3.11
Requires-Dist: aiofiles (>=23.1.0,<24.0.0)
Requires-Dist: filetype (>=1.2.0,<2.0.0)
Requires-Dist: fire (>=0.5.0,<0.6.0)
Requires-Dist: markdown (>=3.4.3,<4.0.0)
Requires-Dist: pydantic (>=1.10.7,<2.0.0)
Requires-Dist: pygments (>=2.15.1,<3.0.0)
Requires-Dist: requests (>=2.31.0,<3.0.0)
Requires-Dist: starlette (>=0.26.1,<0.27.0)
Requires-Dist: urllib3 (>=1.26,<2.0)
Requires-Dist: uvicorn (>=0.21.1,<0.22.0)
Requires-Dist: uvloop (>=0.17.0,<0.18.0)
Requires-Dist: watchfiles (>=0.19.0,<0.20.0)
Requires-Dist: websockets (>=11.0.1,<12.0.0)
